{
  "variants": {
    "facing=south,part=0": { "model": "estherserver:block/rabbit_sofa_part0" },
    "facing=south,part=1": { "model": "estherserver:block/rabbit_sofa_part1" },
    "facing=south,part=2": { "model": "estherserver:block/rabbit_sofa_part2" },
    "facing=south,part=3": { "model": "estherserver:block/rabbit_sofa_part3" },
    "facing=south,part=4": { "model": "estherserver:block/rabbit_sofa_part4" },
    "facing=south,part=5": { "model": "estherserver:block/rabbit_sofa_part5" },
    "facing=south,part=6": { "model": "estherserver:block/rabbit_sofa_part6" },

    "facing=north,part=0": { "model": "estherserver:block/rabbit_sofa_part0", "y": 180 },
    "facing=north,part=1": { "model": "estherserver:block/rabbit_sofa_part1", "y": 180 },
    "facing=north,part=2": { "model": "estherserver:block/rabbit_sofa_part2", "y": 180 },
    "facing=north,part=3": { "model": "estherserver:block/rabbit_sofa_part3", "y": 180 },
    "facing=north,part=4": { "model": "estherserver:block/rabbit_sofa_part4", "y": 180 },
    "facing=north,part=5": { "model": "estherserver:block/rabbit_sofa_part5", "y": 180 },
    "facing=north,part=6": { "model": "estherserver:block/rabbit_sofa_part6", "y": 180 },

    "facing=east,part=0": { "model": "estherserver:block/rabbit_sofa_part0", "y": 270 },
    "facing=east,part=1": { "model": "estherserver:block/rabbit_sofa_part1", "y": 270 },
    "facing=east,part=2": { "model": "estherserver:block/rabbit_sofa_part2", "y": 270 },
    "facing=east,part=3": { "model": "estherserver:block/rabbit_sofa_part3", "y": 270 },
    "facing=east,part=4": { "model": "estherserver:block/rabbit_sofa_part4", "y": 270 },
    "facing=east,part=5": { "model": "estherserver:block/rabbit_sofa_part5", "y": 270 },
    "facing=east,part=6": { "model": "estherserver:block/rabbit_sofa_part6", "y": 270 },

    "facing=west,part=0": { "model": "estherserver:block/rabbit_sofa_part0", "y": 90 },
    "facing=west,part=1": { "model": "estherserver:block/rabbit_sofa_part1", "y": 90 },
    "facing=west,part=2": { "model": "estherserver:block/rabbit_sofa_part2", "y": 90 },
    "facing=west,part=3": { "model": "estherserver:block/rabbit_sofa_part3", "y": 90 },
    "facing=west,part=4": { "model": "estherserver:block/rabbit_sofa_part4", "y": 90 },
    "facing=west,part=5": { "model": "estherserver:block/rabbit_sofa_part5", "y": 90 },
    "facing=west,part=6": { "model": "estherserver:block/rabbit_sofa_part6", "y": 90 }
  }
}